Bering/__init__.py
Bering/_logger.py
Bering/datasets/__init__.py
Bering/datasets/_dataset.py
Bering/datasets/_models.py
Bering/datasets/_utils.py
Bering/graphs/__init__.py
Bering/graphs/_graph.py
Bering/graphs/_graph_raw.py
Bering/graphs/_loader.py
Bering/graphs/_settings.py
Bering/models/__init__.py
Bering/models/_edge_process.py
Bering/models/_edgeclf.py
Bering/models/_gnn.py
Bering/models/_image_model.py
Bering/models/_mlp.py
Bering/models/_utils.py
Bering/objects/__init__.py
Bering/objects/bering.py
Bering/plotting/__init__.py
Bering/plotting/_plot_elements.py
Bering/plotting/_settings.py
Bering/plotting/plot.py
Bering/plotting/plot_post.py
Bering/plotting/scatterplots.py
Bering/plotting/trainplots.py
Bering/preprocess/__init__.py
Bering/preprocess/_image_features.py
Bering/preprocess/_image_preprocessing.py
Bering/segment/__init__.py
Bering/segment/_link_prediction_clustering.py
Bering/segment/_link_prediction_clustering_p.py
Bering/segment/_settings.py
Bering/tools/__init__.py
Bering/tools/_cell_annotation.py
Bering/tools/_cell_segmentation.py
Bering/tools/_coarse_labels.py
Bering/tools/_node_classification.py
Bering/tools_parallel/__init__.py
Bering/tools_parallel/_cell_annotation_p.py
Bering/tools_parallel/_cell_segmentation_p.py
Bering/tools_parallel/_node_classification_p.py
Bering/training/__init__.py
Bering/training/_record.py
Bering/training/_settings.py
Bering/training/_trainer_edge.py
Bering/training/_trainer_node.py
Bering/training/train.py
Bering/transfer/__init__.py
Bering/transfer/_prepare_data.py
Bering-0.1.2.dist-info/LICENSE.md
Bering-0.1.2.dist-info/METADATA
Bering-0.1.2.dist-info/WHEEL
Bering-0.1.2.dist-info/top_level.txt
Bering-0.1.2.dist-info/RECORD
