Metadata-Version: 2.1
Name: Bering
Version: 0.1.2
Summary: Bering: Transfer Learning of Cell Segmentation and Annotation for Spatial Omics
Home-page: https://github.com/KANG-BIOINFO/Bering
Author: Kang Jin
Author-email: kangjin@fas.harvard.edu
Maintainer: Kang Jin
Project-URL: Ducumentation, https://celldrift.readthedocs.io/en/latest/index.html#
License-File: LICENSE.md
Requires-Dist: numpy
Requires-Dist: pandas
Requires-Dist: anndata>=0.8.0
Requires-Dist: scanpy>=1.6.0
Requires-Dist: matplotlib
Requires-Dist: scipy
Requires-Dist: scikit-learn
Requires-Dist: igraph
Requires-Dist: leidenalg
Requires-Dist: torch>=1.12.1
Requires-Dist: torch-geometric>=2.1.0
